pydaq/__init__.py
pydaq/get_data.py
pydaq/get_model.py
pydaq/pydaq_global.py
pydaq/send_data.py
pydaq/step_response.py
pydaq/arduino_code/arduino_code.ino
pydaq/guis/__init__.py
pydaq/guis/error_window_gui.py
pydaq/guis/getdata_arduino_widget.py
pydaq/guis/getdata_nidaq_widget.py
pydaq/guis/getmodel_arduino_widget.py
pydaq/guis/getmodel_nidaq_widget.py
pydaq/guis/getmodel_sysconfig_arduino_widget.py
pydaq/guis/prbs_config_widget.py
pydaq/guis/senddata_arduino_widget.py
pydaq/guis/senddata_nidaq_widget.py
pydaq/guis/stepresponse_arduino_widget.py
pydaq/guis/stepresponse_nidaq_widget.py
pydaq/tests/__init__.py
pydaq/tests/tests_pydaq.py
pydaq/uis/Error_window.ui
pydaq/uis/PRBS_Info_widget.ui
pydaq/uis/PyDAQ_Base.ui
pydaq/uis/PyDAQ_get_data_Arduino_widget.ui
pydaq/uis/PyDAQ_get_data_NIDAQ_widget.ui
pydaq/uis/PyDAQ_get_model_Arduino_widget.ui
pydaq/uis/PyDAQ_get_model_NIDAQ_widget.ui
pydaq/uis/PyDAQ_get_model_sysconfig_Arduino_widget.ui
pydaq/uis/PyDAQ_send_data_Arduino_widget.ui
pydaq/uis/PyDAQ_send_data_NIDAQ_widget.ui
pydaq/uis/PyDAQ_step_response_Arduino_widget.ui
pydaq/uis/PyDAQ_step_response_NIDAQ_widget.ui
pydaq/uis/__init__.py
pydaq/uis/resources_1.qrc
pydaq/uis/resources_1_rc.py
pydaq/uis/ui_Error_window.py
pydaq/uis/ui_PRBS_Info_widget.py
pydaq/uis/ui_PyDAQ_Base.py
pydaq/uis/ui_PyDAQ_get_data_Arduino_widget.py
pydaq/uis/ui_PyDAQ_get_data_NIDAQ_widget.py
pydaq/uis/ui_PyDAQ_get_model_Arduino_widget.py
pydaq/uis/ui_PyDAQ_get_model_NIDAQ_widget.py
pydaq/uis/ui_PyDAQ_get_model_sysconfig_Arduino_widget.py
pydaq/uis/ui_PyDAQ_send_data_Arduino_widget.py
pydaq/uis/ui_PyDAQ_send_data_NIDAQ_widget.py
pydaq/uis/ui_PyDAQ_step_response_Arduino_widget.py
pydaq/uis/ui_PyDAQ_step_response_NIDAQ_widget.py
pydaq/uis/imgs/drop_down_arrow.png
pydaq/uis/imgs/drop_up_arrow.png
pydaq/uis/imgs/favicon.ico
pydaq/uis/imgs/logo.png
pydaq/uis/imgs/pydaq_logo.png
pydaq/uis/imgs/reload.png
pydaq/utils/base.py
pydaq/utils/signals.py
pydaq-0.0.5.1.dist-info/LICENSE
pydaq-0.0.5.1.dist-info/METADATA
pydaq-0.0.5.1.dist-info/WHEEL
pydaq-0.0.5.1.dist-info/top_level.txt
pydaq-0.0.5.1.dist-info/RECORD
