Metadata-Version: 2.2
Name: pydaq
Version: 0.0.5.1
Summary: Data Acquisition and Experimental Analysis with Python
Author-email: Samir Angelo Milani Martins <milani.martins@gmail.com>
License: BSD 3-Clause License
Project-URL: homepage, https://pydaq.org/
Project-URL: repository, https://github.com/samirmartins/pydaq
Project-URL: documentation, https://pydaq.org/
Keywords: Python,Data Acquisition,Arduino,NIDAQ
Classifier: Intended Audience :: Science/Research
Classifier: Intended Audience :: Information Technology
Classifier: Intended Audience :: Developers
Classifier: Intended Audience :: Education
Classifier: License :: OSI Approved :: BSD License
Classifier: Programming Language :: Python :: 3
Classifier: Development Status :: 5 - Production/Stable
Classifier: Topic :: Scientific/Engineering
Classifier: Topic :: Software Development
Classifier: Topic :: Scientific/Engineering :: Artificial Intelligence
Classifier: Topic :: Software Development :: Libraries :: Application Frameworks
Classifier: Topic :: Software Development :: Libraries :: Python Modules
Classifier: Topic :: Software Development :: Libraries
Classifier: Operating System :: OS Independent
Requires-Python: >=3.7
License-File: LICENSE
Requires-Dist: numpy
Requires-Dist: nidaqmx
Requires-Dist: matplotlib
Requires-Dist: pyserial
Requires-Dist: packaging
Requires-Dist: PySide6
Requires-Dist: PySide6_Addons
Requires-Dist: PySide6_Essentials
Requires-Dist: shiboken6
Requires-Dist: sysidentpy==0.3.4
Requires-Dist: bitarray
